<Sql TableName="PMTemplateListSS" TableSchemaXml="#CDATA">
    <CDATA name="TableSchemaXml"><![CDATA[<table name="PMTemplateListSS">
<col name="CompanyID" type="Int" default="Zero" />
<col name="TemplateSS" type="NVarChar(20)" />
<col name="TemplateName" type="NVarChar(255)" />
<col name="CreatedByID" type="UniqueIdentifier" />
<col name="CreatedByScreenID" type="Char(8)" />
<col name="CreatedDateTime" type="DateTime" />
<col name="LastModifiedByID" type="UniqueIdentifier" />
<col name="LastModifiedByScreenID" type="Char(8)" />
<col name="LastModifiedDateTime" type="DateTime" />
<col name="tstamp" type="Timestamp" />
<index name="PMTemplateListSS_PK" clustered="true" primary="true" unique="true">
<col name="CompanyID" />
<col name="TemplateSS" />
<col name="TemplateName" />
</index>
</table>]]></CDATA>
</Sql>